netbox_script_manager/__init__.py
netbox_script_manager/choices.py
netbox_script_manager/filtersets.py
netbox_script_manager/forms.py
netbox_script_manager/models.py
netbox_script_manager/navigation.py
netbox_script_manager/scripts.py
netbox_script_manager/tables.py
netbox_script_manager/urls.py
netbox_script_manager/util.py
netbox_script_manager/views.py
netbox_script_manager/api/__init__.py
netbox_script_manager/api/serializers.py
netbox_script_manager/api/urls.py
netbox_script_manager/api/views.py
netbox_script_manager/migrations/0001_initial.py
netbox_script_manager/migrations/0002_scriptexecution_last_updated.py
netbox_script_manager/migrations/0003_scriptinstance_tenant.py
netbox_script_manager/migrations/__init__.py
netbox_script_manager/static/netbox_script_manager/main.js
netbox_script_manager/templates/netbox_script_manager/script_artifact_htmx_table.html
netbox_script_manager/templates/netbox_script_manager/script_execution_objectchange_list.html
netbox_script_manager/templates/netbox_script_manager/script_instance_execution_list.html
netbox_script_manager/templates/netbox_script_manager/script_list.html
netbox_script_manager/templates/netbox_script_manager/scriptexecution.html
netbox_script_manager/templates/netbox_script_manager/scriptexecution_data.html
netbox_script_manager/templates/netbox_script_manager/scriptinstance.html
netbox_script_manager/templates/netbox_script_manager/htmx/script_execution.html
netbox_script_manager/templatetags/__init__.py
netbox_script_manager/templatetags/scriptmanager.py
tests/__init__.py
tests/test_netbox_script_manager.py
netbox_script_manager-1.1.0.dist-info/LICENSE
netbox_script_manager-1.1.0.dist-info/METADATA
netbox_script_manager-1.1.0.dist-info/WHEEL
netbox_script_manager-1.1.0.dist-info/top_level.txt
netbox_script_manager-1.1.0.dist-info/RECORD
