Metadata-Version: 2.2
Name: netbox-script-manager
Version: 1.1.0
Summary: Improved custom script support for netbox
Home-page: https://github.com/kkthxbye-code/netbox_script_manager
Author: kkthxbye-code
Author-email: festll234@gmail.com
Keywords: netbox,netbox-plugin
Classifier: Development Status :: 2 - Pre-Alpha
Classifier: Intended Audience :: Developers
Classifier: Natural Language :: English
Classifier: Programming Language :: Python :: 3
Classifier: Programming Language :: Python :: 3.8
Classifier: Programming Language :: Python :: 3.9
Classifier: Programming Language :: Python :: 3.10
Classifier: Programming Language :: Python :: 3.11
Requires-Python: >=3.8
License-File: LICENSE
Dynamic: author
Dynamic: author-email
Dynamic: classifier
Dynamic: description
Dynamic: description-content-type
Dynamic: home-page
Dynamic: keywords
Dynamic: requires-python
Dynamic: summary
